ebook2audiobook/.DS_Store
ebook2audiobook/__init__.py
ebook2audiobook/app.py
ebook2audiobook/default_voice.wav
ebook2audiobook-0.0.7.dist-info/LICENSE.txt
ebook2audiobook-0.0.7.dist-info/METADATA
ebook2audiobook-0.0.7.dist-info/WHEEL
ebook2audiobook-0.0.7.dist-info/entry_points.txt
ebook2audiobook-0.0.7.dist-info/top_level.txt
ebook2audiobook-0.0.7.dist-info/RECORD
