Metadata-Version: 2.1
Name: ebook2audiobook
Version: 0.0.7
Summary: Convert eBooks to Audiobooks using a Text-to-Speech model with optional Gradio interface.
Home-page: https://github.com/DrewThomasson/ebook2audiobookXTTS
Author: Andrew Phillip Thomasson
Author-email: drew.thomasson100@gmail.com
Classifier: Programming Language :: Python :: 3
Classifier: License :: OSI Approved :: MIT License
Classifier: Operating System :: OS Independent
Requires-Python: >=3.7, <3.13
License-File: LICENSE.txt
Requires-Dist: coqui-tts==0.24.2
Requires-Dist: pydub
Requires-Dist: nltk
Requires-Dist: beautifulsoup4
Requires-Dist: ebooklib
Requires-Dist: tqdm
Requires-Dist: gradio==4.44.1
